utf_queue_client/__init__.py
utf_queue_client/clients/__init__.py
utf_queue_client/clients/async_consumer.py
utf_queue_client/clients/base_producer.py
utf_queue_client/clients/data_lake_data_producer.py
utf_queue_client/clients/http_producer.py
utf_queue_client/clients/opentelemetry_data_producer.py
utf_queue_client/clients/sqa_test_result_producer.py
utf_queue_client/clients/test_rail_data_producer.py
utf_queue_client/clients/ubai_artifact_upload_request_producer.py
utf_queue_client/clients/xray_data_producer.py
utf_queue_client/exceptions/__init__.py
utf_queue_client/models/__init__.py
utf_queue_client/models/base_model.py
utf_queue_client/models/model_factory.py
utf_queue_client/models/schemas/__init__.py
utf_queue_client/models/schemas/utf_queue_models/models/python/__init__.py
utf_queue_client/models/schemas/utf_queue_models/models/python/generated_models.py
utf_queue_client/models/schemas/utf_queue_models/models/python/generated_models_pydantic_v1.py
utf_queue_client/models/schemas/utf_queue_models/models/python/generated_models_pydantic_v2.py
utf_queue_client/models/schemas/utf_queue_models/schema/queue_message.json
utf_queue_client/scripts/__init__.py
utf_queue_client/scripts/publish_release_info_cli.py
utf_queue_client/scripts/publish_test_results_cli.py
utf_queue_client/scripts/ubai_copy_cli.py
utf_queue_client/scripts/ubai_search_cli.py
utf_queue_client/scripts/ubai_update_retention_cli.py
utf_queue_client/scripts/ubai_upload_cli.py
utf_queue_client/utils/__init__.py
utf_queue_client/utils/queue_metrics_exporter.py
utf_queue_client/utils/queue_span_exporter.py
utf_queue_client-1.21.3.dist-info/METADATA
utf_queue_client-1.21.3.dist-info/WHEEL
utf_queue_client-1.21.3.dist-info/entry_points.txt
utf_queue_client-1.21.3.dist-info/top_level.txt
utf_queue_client-1.21.3.dist-info/RECORD
